{"columnName": ["category_name", "total_enrol", "upper_primary_b", "upper_primary_g", "higher_secondary_b", "loc_name", "higher_secondary_g", "c10_g", "cpp", "c12_g", "upper_primary_total", "c12_b", "c1", "c2", "c10_b", "c3", "c4", "c7_g", "secondary_g", "c5", "location_name", "c6", "c9_g", "c7", "c9_b", "c3_g", "c8", "c9", "c5_g", "c5_b", "c7_b", "secondary_b", "c1_g", "c1_b", "c3_b", "sch_mgmt_name", "c11", "c10", "total_pre_enrol", "c12", "secondary_total", "primary_b", "primary_g", "cpp_b", "c11_g", "total_g", "total_pre_b", "higher_secondary_total", "total_b", "cpp_g", "c11_b", "c8_g", "c4_g", "c8_b", "c6_g", "c4_b", "c2_g", "total_pre_g", "c6_b", "primary_total", "c2_b"], "rowValue": [{"category_name": "PS (I-V) ", "total_enrol": 4166196, "upper_primary_b": 368566, "upper_primary_g": 402771, "higher_secondary_b": 6020, "loc_name": "Rural", "higher_secondary_g": 6624, "c10_g": 15760, "cpp": 20530, "c12_g": 3380, "upper_primary_total": 771337, "c12_b": 3271, "c1": 663757, "c2": 726745, "c10_b": 15946, "c3": 739970, "c4": 761045, "c7_g": 171522, "secondary_g": 32499, "c5": 425277, "location_name": "Maharashtra", "c6": 343495, "c9_g": 16739, "c7": 327165, "c9_b": 16976, "c3_g": 363343, "c8": 100677, "c9": 33715, "c5_g": 214395, "c5_b": 210882, "c7_b": 155643, "secondary_b": 32922, "c1_g": 333796, "c1_b": 329961, "c3_b": 376627, "sch_mgmt_name": "Local body", "c11": 5993, "c10": 31706, "total_pre_enrol": 4186726, "c12": 6651, "secondary_total": 65421, "primary_b": 1669388, "primary_g": 1647406, "cpp_b": 10628, "c11_g": 3244, "total_g": 2089300, "total_pre_b": 2087524, "higher_secondary_total": 12644, "total_b": 2076896, "cpp_g": 9902, "c11_b": 2749, "c8_g": 53727, "c4_g": 372874, "c8_b": 46950, "c6_g": 177522, "c4_b": 388171, "c2_g": 362998, "total_pre_g": 2099202, "c6_b": 165973, "primary_total": 3316794, "c2_b": 363747}, {"category_name": "PS (I-V) ", "total_enrol": 1594, "upper_primary_b": 262, "upper_primary_g": 223, "higher_secondary_b": 92, "loc_name": "Rural", "higher_secondary_g": 63, "c10_g": 63, "cpp": 0, "c12_g": 8, "upper_primary_total": 485, "c12_b": 17, "c1": 168, "c2": 134, "c10_b": 72, "c3": 105, "c4": 134, "c7_g": 74, "secondary_g": 127, "c5": 121, "location_name": "Maharashtra", "c6": 189, "c9_g": 64, "c7": 162, "c9_b": 93, "c3_g": 50, "c8": 134, "c9": 157, "c5_g": 52, "c5_b": 69, "c7_b": 88, "secondary_b": 165, "c1_g": 75, "c1_b": 93, "c3_b": 55, "sch_mgmt_name": "Railway School", "c11": 130, "c10": 135, "total_pre_enrol": 1594, "c12": 25, "secondary_total": 292, "primary_b": 371, "primary_g": 291, "cpp_b": 0, "c11_g": 55, "total_g": 704, "total_pre_b": 890, "higher_secondary_total": 155, "total_b": 890, "cpp_g": 0, "c11_b": 75, "c8_g": 63, "c4_g": 55, "c8_b": 71, "c6_g": 86, "c4_b": 79, "c2_g": 59, "total_pre_g": 704, "c6_b": 103, "primary_total": 662, "c2_b": 75}, {"category_name": "PS (I-V) ", "total_enrol": 197649, "upper_primary_b": 32598, "upper_primary_g": 34754, "higher_secondary_b": 9776, "loc_name": "Rural", "higher_secondary_g": 11177, "c10_g": 10124, "cpp": 0, "c12_g": 5700, "upper_primary_total": 67352, "c12_b": 5138, "c1": 10748, "c2": 11753, "c10_b": 9411, "c3": 12104, "c4": 13333, "c7_g": 11464, "secondary_g": 21247, "c5": 19856, "location_name": "Maharashtra", "c6": 22805, "c9_g": 11123, "c7": 22196, "c9_b": 10892, "c3_g": 6242, "c8": 22351, "c9": 22015, "c5_g": 10225, "c5_b": 9631, "c7_b": 10732, "secondary_b": 20303, "c1_g": 5625, "c1_b": 5123, "c3_b": 5862, "sch_mgmt_name": "Tribal Welfare Department", "c11": 10115, "c10": 19535, "total_pre_enrol": 197649, "c12": 10838, "secondary_total": 41550, "primary_b": 32732, "primary_g": 35062, "cpp_b": 0, "c11_g": 5477, "total_g": 102240, "total_pre_b": 95409, "higher_secondary_total": 20953, "total_b": 95409, "cpp_g": 0, "c11_b": 4638, "c8_g": 11498, "c4_g": 6828, "c8_b": 10853, "c6_g": 11792, "c4_b": 6505, "c2_g": 6142, "total_pre_g": 102240, "c6_b": 11013, "primary_total": 67794, "c2_b": 5611}, {"category_name": "PS (I-V) ", "total_enrol": 15235, "upper_primary_b": 2178, "upper_primary_g": 1822, "higher_secondary_b": 720, "loc_name": "Rural", "higher_secondary_g": 685, "c10_g": 440, "cpp": 0, "c12_g": 314, "upper_primary_total": 4000, "c12_b": 311, "c1": 1456, "c2": 1531, "c10_b": 557, "c3": 1475, "c4": 1493, "c7_g": 628, "secondary_g": 1043, "c5": 1459, "location_name": "Maharashtra", "c6": 1369, "c9_g": 603, "c7": 1348, "c9_b": 816, "c3_g": 687, "c8": 1283, "c9": 1419, "c5_g": 672, "c5_b": 787, "c7_b": 720, "secondary_b": 1373, "c1_g": 714, "c1_b": 742, "c3_b": 788, "sch_mgmt_name": "Kendriya Vidyalaya / Central School", "c11": 780, "c10": 997, "total_pre_enrol": 15235, "c12": 625, "secondary_total": 2416, "primary_b": 3985, "primary_g": 3429, "cpp_b": 0, "c11_g": 371, "total_g": 6979, "total_pre_b": 8256, "higher_secondary_total": 1405, "total_b": 8256, "cpp_g": 0, "c11_b": 409, "c8_g": 576, "c4_g": 675, "c8_b": 707, "c6_g": 618, "c4_b": 818, "c2_g": 681, "total_pre_g": 6979, "c6_b": 751, "primary_total": 7414, "c2_b": 850}, {"category_name": "PS (I-V) ", "total_enrol": 5006220, "upper_primary_b": 914703, "upper_primary_g": 807909, "higher_secondary_b": 503834, "loc_name": "Rural", "higher_secondary_g": 421157, "c10_g": 354437, "cpp": 20285, "c12_g": 216144, "upper_primary_total": 1722612, "c12_b": 270578, "c1": 86388, "c2": 92351, "c10_b": 413941, "c3": 98217, "c4": 104559, "c7_g": 239247, "secondary_g": 716385, "c5": 438418, "location_name": "Maharashtra", "c6": 495784, "c9_g": 361948, "c7": 516811, "c9_b": 408358, "c3_g": 44272, "c8": 710017, "c9": 770306, "c5_g": 201978, "c5_b": 236440, "c7_b": 277564, "secondary_b": 822299, "c1_g": 40356, "c1_b": 46032, "c3_b": 53945, "sch_mgmt_name": "Government Aided", "c11": 438269, "c10": 768378, "total_pre_enrol": 5026505, "c12": 486722, "secondary_total": 1538684, "primary_b": 443938, "primary_g": 375995, "cpp_b": 10749, "c11_g": 205013, "total_g": 2321446, "total_pre_b": 2695523, "higher_secondary_total": 924991, "total_b": 2684774, "cpp_g": 9536, "c11_b": 233256, "c8_g": 337371, "c4_g": 46651, "c8_b": 372646, "c6_g": 231291, "c4_b": 57908, "c2_g": 42738, "total_pre_g": 2330982, "c6_b": 264493, "primary_total": 819933, "c2_b": 49613}, {"category_name": "PS (I-V) ", "total_enrol": 2031742, "upper_primary_b": 248414, "upper_primary_g": 167330, "higher_secondary_b": 153286, "loc_name": "Rural", "higher_secondary_g": 105790, "c10_g": 48848, "cpp": 214187, "c12_g": 54481, "upper_primary_total": 415744, "c12_b": 84397, "c1": 261284, "c2": 243469, "c10_b": 74070, "c3": 224276, "c4": 207589, "c7_g": 52685, "secondary_g": 102153, "c5": 167900, "location_name": "Maharashtra", "c6": 146304, "c9_g": 53305, "c7": 133025, "c9_b": 76181, "c3_g": 91139, "c8": 136415, "c9": 129486, "c5_g": 67563, "c5_b": 100337, "c7_b": 80340, "secondary_b": 150251, "c1_g": 110450, "c1_b": 150834, "c3_b": 133137, "sch_mgmt_name": "Private Unaided (Recognized)", "c11": 120198, "c10": 122918, "total_pre_enrol": 2245929, "c12": 138878, "secondary_total": 252404, "primary_b": 650435, "primary_g": 454083, "cpp_b": 120496, "c11_g": 51309, "total_g": 829356, "total_pre_b": 1322882, "higher_secondary_total": 259076, "total_b": 1202386, "cpp_g": 93691, "c11_b": 68889, "c8_g": 55884, "c4_g": 83750, "c8_b": 80531, "c6_g": 58761, "c4_b": 123839, "c2_g": 101181, "total_pre_g": 923047, "c6_b": 87543, "primary_total": 1104518, "c2_b": 142288}, {"category_name": "PS (I-V) ", "total_enrol": 27555, "upper_primary_b": 3107, "upper_primary_g": 2275, "higher_secondary_b": 129, "loc_name": "Rural", "higher_secondary_g": 72, "c10_g": 502, "cpp": 6830, "c12_g": 48, "upper_primary_total": 5382, "c12_b": 99, "c1": 5392, "c2": 4569, "c10_b": 1037, "c3": 3716, "c4": 3128, "c7_g": 764, "secondary_g": 1021, "c5": 2318, "location_name": "Maharashtra", "c6": 2058, "c9_g": 519, "c7": 1744, "c9_b": 791, "c3_g": 1661, "c8": 1580, "c9": 1310, "c5_g": 1072, "c5_b": 1246, "c7_b": 980, "secondary_b": 1828, "c1_g": 2444, "c1_b": 2948, "c3_b": 2055, "sch_mgmt_name": "Unrecognized", "c11": 54, "c10": 1539, "total_pre_enrol": 34385, "c12": 147, "secondary_total": 2849, "primary_b": 10596, "primary_g": 8527, "cpp_b": 3743, "c11_g": 24, "total_g": 11895, "total_pre_b": 19403, "higher_secondary_total": 201, "total_b": 15660, "cpp_g": 3087, "c11_b": 30, "c8_g": 637, "c4_g": 1360, "c8_b": 943, "c6_g": 874, "c4_b": 1768, "c2_g": 1990, "total_pre_g": 14982, "c6_b": 1184, "primary_total": 19123, "c2_b": 2579}, {"category_name": "PS (I-V) ", "total_enrol": 10344, "upper_primary_b": 3622, "upper_primary_g": 2309, "higher_secondary_b": 0, "loc_name": "Rural", "higher_secondary_g": 40, "c10_g": 704, "cpp": 0, "c12_g": 40, "upper_primary_total": 5931, "c12_b": 0, "c1": 182, "c2": 170, "c10_b": 968, "c3": 148, "c4": 171, "c7_g": 781, "secondary_g": 1460, "c5": 121, "location_name": "Maharashtra", "c6": 1801, "c9_g": 756, "c7": 2014, "c9_b": 1153, "c3_g": 53, "c8": 2116, "c9": 1909, "c5_g": 36, "c5_b": 85, "c7_b": 1233, "secondary_b": 2121, "c1_g": 61, "c1_b": 121, "c3_b": 95, "sch_mgmt_name": "Social welfare Department", "c11": 0, "c10": 1672, "total_pre_enrol": 10344, "c12": 40, "secondary_total": 3581, "primary_b": 513, "primary_g": 279, "cpp_b": 0, "c11_g": 0, "total_g": 4088, "total_pre_b": 6256, "higher_secondary_total": 40, "total_b": 6256, "cpp_g": 0, "c11_b": 0, "c8_g": 815, "c4_g": 68, "c8_b": 1301, "c6_g": 713, "c4_b": 103, "c2_g": 61, "total_pre_g": 4088, "c6_b": 1088, "primary_total": 792, "c2_b": 109}, {"category_name": "PS (I-V) ", "total_enrol": 1170, "upper_primary_b": 337, "upper_primary_g": 122, "higher_secondary_b": 0, "loc_name": "Rural", "higher_secondary_g": 0, "c10_g": 0, "cpp": 0, "c12_g": 0, "upper_primary_total": 459, "c12_b": 0, "c1": 112, "c2": 111, "c10_b": 30, "c3": 139, "c4": 121, "c7_g": 56, "secondary_g": 12, "c5": 134, "location_name": "Maharashtra", "c6": 164, "c9_g": 12, "c7": 169, "c9_b": 52, "c3_g": 39, "c8": 126, "c9": 64, "c5_g": 31, "c5_b": 103, "c7_b": 113, "secondary_b": 82, "c1_g": 38, "c1_b": 74, "c3_b": 100, "sch_mgmt_name": "Madarsa recognized (by Wakf board/Madarsa Board) ", "c11": 0, "c10": 30, "total_pre_enrol": 1170, "c12": 0, "secondary_total": 94, "primary_b": 432, "primary_g": 185, "cpp_b": 0, "c11_g": 0, "total_g": 319, "total_pre_b": 851, "higher_secondary_total": 0, "total_b": 851, "cpp_g": 0, "c11_b": 0, "c8_g": 29, "c4_g": 46, "c8_b": 97, "c6_g": 37, "c4_b": 75, "c2_g": 31, "total_pre_g": 319, "c6_b": 127, "primary_total": 617, "c2_b": 80}, {"category_name": "PS (I-V) ", "total_enrol": 4461, "upper_primary_b": 985, "upper_primary_g": 1255, "higher_secondary_b": 3, "loc_name": "Rural", "higher_secondary_g": 1, "c10_g": 9, "cpp": 24, "c12_g": 1, "upper_primary_total": 2240, "c12_b": 3, "c1": 410, "c2": 358, "c10_b": 209, "c3": 333, "c4": 345, "c7_g": 546, "secondary_g": 17, "c5": 271, "location_name": "Maharashtra", "c6": 782, "c9_g": 8, "c7": 871, "c9_b": 274, "c3_g": 148, "c8": 587, "c9": 282, "c5_g": 102, "c5_b": 169, "c7_b": 325, "secondary_b": 483, "c1_g": 192, "c1_b": 218, "c3_b": 185, "sch_mgmt_name": "Madarsa unrecognized", "c11": 0, "c10": 218, "total_pre_enrol": 4485, "c12": 4, "secondary_total": 500, "primary_b": 999, "primary_g": 718, "cpp_b": 10, "c11_g": 0, "total_g": 1991, "total_pre_b": 2480, "higher_secondary_total": 4, "total_b": 2470, "cpp_g": 14, "c11_b": 0, "c8_g": 248, "c4_g": 118, "c8_b": 339, "c6_g": 461, "c4_b": 227, "c2_g": 158, "total_pre_g": 2005, "c6_b": 321, "primary_total": 1717, "c2_b": 200}, {"category_name": "PS (I-V) ", "total_enrol": 2849, "upper_primary_b": 400, "upper_primary_g": 362, "higher_secondary_b": 146, "loc_name": "Rural", "higher_secondary_g": 146, "c10_g": 97, "cpp": 217, "c12_g": 75, "upper_primary_total": 762, "c12_b": 67, "c1": 260, "c2": 272, "c10_b": 92, "c3": 307, "c4": 289, "c7_g": 118, "secondary_g": 192, "c5": 278, "location_name": "Maharashtra", "c6": 274, "c9_g": 95, "c7": 257, "c9_b": 105, "c3_g": 150, "c8": 231, "c9": 200, "c5_g": 134, "c5_b": 144, "c7_b": 139, "secondary_b": 197, "c1_g": 124, "c1_b": 136, "c3_b": 157, "sch_mgmt_name": "Other Central Govt. Schools", "c11": 150, "c10": 189, "total_pre_enrol": 3066, "c12": 142, "secondary_total": 389, "primary_b": 711, "primary_g": 695, "cpp_b": 115, "c11_g": 71, "total_g": 1395, "total_pre_b": 1569, "higher_secondary_total": 292, "total_b": 1454, "cpp_g": 102, "c11_b": 79, "c8_g": 109, "c4_g": 150, "c8_b": 122, "c6_g": 135, "c4_b": 139, "c2_g": 137, "total_pre_g": 1497, "c6_b": 139, "primary_total": 1406, "c2_b": 135}, {"category_name": "PS (I-V) ", "total_enrol": 921, "upper_primary_b": 264, "upper_primary_g": 159, "higher_secondary_b": 175, "loc_name": "Rural", "higher_secondary_g": 0, "c10_g": 40, "cpp": 0, "c12_g": 0, "upper_primary_total": 423, "c12_b": 92, "c1": 9, "c2": 6, "c10_b": 92, "c3": 11, "c4": 13, "c7_g": 67, "secondary_g": 84, "c5": 18, "location_name": "Maharashtra", "c6": 115, "c9_g": 44, "c7": 157, "c9_b": 90, "c3_g": 4, "c8": 151, "c9": 134, "c5_g": 8, "c5_b": 10, "c7_b": 90, "secondary_b": 182, "c1_g": 4, "c1_b": 5, "c3_b": 7, "sch_mgmt_name": "Department of Education", "c11": 83, "c10": 132, "total_pre_enrol": 921, "c12": 92, "secondary_total": 266, "primary_b": 34, "primary_g": 23, "cpp_b": 0, "c11_g": 0, "total_g": 266, "total_pre_b": 655, "higher_secondary_total": 175, "total_b": 655, "cpp_g": 0, "c11_b": 83, "c8_g": 49, "c4_g": 4, "c8_b": 102, "c6_g": 43, "c4_b": 9, "c2_g": 3, "total_pre_g": 266, "c6_b": 72, "primary_total": 57, "c2_b": 3}, {"category_name": "PS (I-V) ", "total_enrol": 12534, "upper_primary_b": 3513, "upper_primary_g": 2546, "higher_secondary_b": 1458, "loc_name": "Rural", "higher_secondary_g": 1015, "c10_g": 828, "cpp": 0, "c12_g": 482, "upper_primary_total": 6059, "c12_b": 679, "c1": 0, "c2": 0, "c10_b": 1129, "c3": 0, "c4": 0, "c7_g": 917, "secondary_g": 1713, "c5": 0, "location_name": "Maharashtra", "c6": 2053, "c9_g": 885, "c7": 2068, "c9_b": 1160, "c3_g": 0, "c8": 1938, "c9": 2045, "c5_g": 0, "c5_b": 0, "c7_b": 1151, "secondary_b": 2289, "c1_g": 0, "c1_b": 0, "c3_b": 0, "sch_mgmt_name": "Jawahar Navodaya Vidyalaya ", "c11": 1312, "c10": 1957, "total_pre_enrol": 12534, "c12": 1161, "secondary_total": 4002, "primary_b": 0, "primary_g": 0, "cpp_b": 0, "c11_g": 533, "total_g": 5274, "total_pre_b": 7260, "higher_secondary_total": 2473, "total_b": 7260, "cpp_g": 0, "c11_b": 779, "c8_g": 819, "c4_g": 0, "c8_b": 1119, "c6_g": 810, "c4_b": 0, "c2_g": 0, "total_pre_g": 5274, "c6_b": 1243, "primary_total": 0, "c2_b": 0}, {"category_name": "PS (I-V) ", "total_enrol": 90, "upper_primary_b": 90, "upper_primary_g": 0, "higher_secondary_b": 0, "loc_name": "Rural", "higher_secondary_g": 0, "c10_g": 0, "cpp": 0, "c12_g": 0, "upper_primary_total": 90, "c12_b": 0, "c1": 0, "c2": 0, "c10_b": 0, "c3": 0, "c4": 0, "c7_g": 0, "secondary_g": 0, "c5": 0, "location_name": "Maharashtra", "c6": 90, "c9_g": 0, "c7": 0, "c9_b": 0, "c3_g": 0, "c8": 0, "c9": 0, "c5_g": 0, "c5_b": 0, "c7_b": 0, "secondary_b": 0, "c1_g": 0, "c1_b": 0, "c3_b": 0, "sch_mgmt_name": "Sainik School", "c11": 0, "c10": 0, "total_pre_enrol": 90, "c12": 0, "secondary_total": 0, "primary_b": 0, "primary_g": 0, "cpp_b": 0, "c11_g": 0, "total_g": 0, "total_pre_b": 90, "higher_secondary_total": 0, "total_b": 90, "cpp_g": 0, "c11_b": 0, "c8_g": 0, "c4_g": 0, "c8_b": 0, "c6_g": 0, "c4_b": 0, "c2_g": 0, "total_pre_g": 0, "c6_b": 90, "primary_total": 0, "c2_b": 0}, {"category_name": "PS (I-V) ", "total_enrol": 9568, "upper_primary_b": 400, "upper_primary_g": 110, "higher_secondary_b": 5414, "loc_name": "Urban", "higher_secondary_g": 2472, "c10_g": 38, "cpp": 35, "c12_g": 1225, "upper_primary_total": 510, "c12_b": 2648, "c1": 139, "c2": 111, "c10_b": 195, "c3": 144, "c4": 136, "c7_g": 37, "secondary_g": 90, "c5": 92, "location_name": "Maharashtra", "c6": 135, "c9_g": 52, "c7": 151, "c9_b": 265, "c3_g": 62, "c8": 224, "c9": 317, "c5_g": 38, "c5_b": 54, "c7_b": 114, "secondary_b": 460, "c1_g": 59, "c1_b": 80, "c3_b": 82, "sch_mgmt_name": "Department of Education", "c11": 4013, "c10": 233, "total_pre_enrol": 9603, "c12": 3873, "secondary_total": 550, "primary_b": 337, "primary_g": 285, "cpp_b": 13, "c11_g": 1247, "total_g": 2957, "total_pre_b": 6624, "higher_secondary_total": 7886, "total_b": 6611, "cpp_g": 22, "c11_b": 2766, "c8_g": 43, "c4_g": 74, "c8_b": 181, "c6_g": 30, "c4_b": 62, "c2_g": 52, "total_pre_g": 2979, "c6_b": 105, "primary_total": 622, "c2_b": 59}, {"category_name": "PS (I-V) ", "total_enrol": 1039713, "upper_primary_b": 147237, "upper_primary_g": 153339, "higher_secondary_b": 10343, "loc_name": "Urban", "higher_secondary_g": 11020, "c10_g": 24211, "cpp": 82560, "c12_g": 5592, "upper_primary_total": 300576, "c12_b": 5250, "c1": 112249, "c2": 121828, "c10_b": 22698, "c3": 128416, "c4": 134352, "c7_g": 55426, "secondary_g": 52622, "c5": 115890, "location_name": "Maharashtra", "c6": 112414, "c9_g": 28411, "c7": 108573, "c9_b": 29719, "c3_g": 65151, "c8": 79589, "c9": 58130, "c5_g": 58600, "c5_b": 57290, "c7_b": 53147, "secondary_b": 52417, "c1_g": 57081, "c1_b": 55168, "c3_b": 63265, "sch_mgmt_name": "Local body", "c11": 10521, "c10": 46909, "total_pre_enrol": 1122273, "c12": 10842, "secondary_total": 105039, "primary_b": 301924, "primary_g": 310811, "cpp_b": 41280, "c11_g": 5428, "total_g": 527792, "total_pre_b": 553201, "higher_secondary_total": 21363, "total_b": 511921, "cpp_g": 41280, "c11_b": 5093, "c8_g": 40428, "c4_g": 68000, "c8_b": 39161, "c6_g": 57485, "c4_b": 66352, "c2_g": 61979, "total_pre_g": 569072, "c6_b": 54929, "primary_total": 612735, "c2_b": 59849}, {"category_name": "PS (I-V) ", "total_enrol": 5409967, "upper_primary_b": 794863, "upper_primary_g": 730919, "higher_secondary_b": 574730, "loc_name": "Urban", "higher_secondary_g": 573145, "c10_g": 259941, "cpp": 152288, "c12_g": 285830, "upper_primary_total": 1525782, "c12_b": 289941, "c1": 269132, "c2": 287074, "c10_b": 265756, "c3": 303972, "c4": 320997, "c7_g": 237531, "secondary_g": 536662, "c5": 450657, "location_name": "Maharashtra", "c6": 486028, "c9_g": 276721, "c7": 497614, "c9_b": 302060, "c3_g": 147220, "c8": 542140, "c9": 578781, "c5_g": 216201, "c5_b": 234456, "c7_b": 260083, "secondary_b": 567816, "c1_g": 132556, "c1_b": 136576, "c3_b": 156752, "sch_mgmt_name": "Government Aided", "c11": 572104, "c10": 525697, "total_pre_enrol": 5562255, "c12": 575771, "secondary_total": 1104478, "primary_b": 841243, "primary_g": 790589, "cpp_b": 76278, "c11_g": 287315, "total_g": 2631315, "total_pre_b": 2854930, "higher_secondary_total": 1147875, "total_b": 2778652, "cpp_g": 76010, "c11_b": 284789, "c8_g": 260900, "c4_g": 153975, "c8_b": 281240, "c6_g": 232488, "c4_b": 167022, "c2_g": 140637, "total_pre_g": 2707325, "c6_b": 253540, "primary_total": 1631832, "c2_b": 146437}, {"category_name": "PS (I-V) ", "total_enrol": 5093, "upper_primary_b": 1754, "upper_primary_g": 1140, "higher_secondary_b": 0, "loc_name": "Urban", "higher_secondary_g": 0, "c10_g": 327, "cpp": 0, "c12_g": 0, "upper_primary_total": 2894, "c12_b": 0, "c1": 111, "c2": 107, "c10_b": 433, "c3": 102, "c4": 101, "c7_g": 392, "secondary_g": 712, "c5": 82, "location_name": "Maharashtra", "c6": 896, "c9_g": 385, "c7": 978, "c9_b": 551, "c3_g": 34, "c8": 1020, "c9": 936, "c5_g": 26, "c5_b": 56, "c7_b": 586, "secondary_b": 984, "c1_g": 32, "c1_b": 79, "c3_b": 68, "sch_mgmt_name": "Social welfare Department", "c11": 0, "c10": 760, "total_pre_enrol": 5093, "c12": 0, "secondary_total": 1696, "primary_b": 352, "primary_g": 151, "cpp_b": 0, "c11_g": 0, "total_g": 2003, "total_pre_b": 3090, "higher_secondary_total": 0, "total_b": 3090, "cpp_g": 0, "c11_b": 0, "c8_g": 397, "c4_g": 35, "c8_b": 623, "c6_g": 351, "c4_b": 66, "c2_g": 24, "total_pre_g": 2003, "c6_b": 545, "primary_total": 503, "c2_b": 83}, {"category_name": "PS (I-V) ", "total_enrol": 1702, "upper_primary_b": 237, "upper_primary_g": 164, "higher_secondary_b": 131, "loc_name": "Urban", "higher_secondary_g": 89, "c10_g": 47, "cpp": 355, "c12_g": 41, "upper_primary_total": 401, "c12_b": 55, "c1": 186, "c2": 145, "c10_b": 86, "c3": 153, "c4": 169, "c7_g": 57, "secondary_g": 101, "c5": 162, "location_name": "Maharashtra", "c6": 132, "c9_g": 54, "c7": 131, "c9_b": 79, "c3_g": 59, "c8": 138, "c9": 133, "c5_g": 64, "c5_b": 98, "c7_b": 74, "secondary_b": 165, "c1_g": 85, "c1_b": 101, "c3_b": 94, "sch_mgmt_name": "Railway School", "c11": 124, "c10": 133, "total_pre_enrol": 2057, "c12": 96, "secondary_total": 266, "primary_b": 474, "primary_g": 341, "cpp_b": 193, "c11_g": 48, "total_g": 695, "total_pre_b": 1200, "higher_secondary_total": 220, "total_b": 1007, "cpp_g": 162, "c11_b": 76, "c8_g": 53, "c4_g": 69, "c8_b": 85, "c6_g": 54, "c4_b": 100, "c2_g": 64, "total_pre_g": 857, "c6_b": 78, "primary_total": 815, "c2_b": 81}, {"category_name": "PS (I-V) ", "total_enrol": 903, "upper_primary_b": 89, "upper_primary_g": 34, "higher_secondary_b": 0, "loc_name": "Urban", "higher_secondary_g": 0, "c10_g": 0, "cpp": 128, "c12_g": 0, "upper_primary_total": 123, "c12_b": 0, "c1": 354, "c2": 127, "c10_b": 0, "c3": 105, "c4": 106, "c7_g": 8, "secondary_g": 0, "c5": 88, "location_name": "Maharashtra", "c6": 47, "c9_g": 0, "c7": 40, "c9_b": 0, "c3_g": 69, "c8": 36, "c9": 0, "c5_g": 40, "c5_b": 48, "c7_b": 32, "secondary_b": 0, "c1_g": 201, "c1_b": 153, "c3_b": 36, "sch_mgmt_name": "Madarsa recognized (by Wakf board/Madarsa Board) ", "c11": 0, "c10": 0, "total_pre_enrol": 1031, "c12": 0, "secondary_total": 0, "primary_b": 337, "primary_g": 443, "cpp_b": 56, "c11_g": 0, "total_g": 477, "total_pre_b": 482, "higher_secondary_total": 0, "total_b": 426, "cpp_g": 72, "c11_b": 0, "c8_g": 9, "c4_g": 52, "c8_b": 27, "c6_g": 17, "c4_b": 54, "c2_g": 81, "total_pre_g": 549, "c6_b": 30, "primary_total": 780, "c2_b": 46}, {"category_name": "PS (I-V) ", "total_enrol": 7075, "upper_primary_b": 1958, "upper_primary_g": 377, "higher_secondary_b": 10, "loc_name": "Urban", "higher_secondary_g": 26, "c10_g": 3, "cpp": 130, "c12_g": 0, "upper_primary_total": 2335, "c12_b": 2, "c1": 980, "c2": 971, "c10_b": 8, "c3": 931, "c4": 924, "c7_g": 134, "secondary_g": 18, "c5": 865, "location_name": "Maharashtra", "c6": 818, "c9_g": 15, "c7": 858, "c9_b": 7, "c3_g": 256, "c8": 659, "c9": 22, "c5_g": 211, "c5_b": 654, "c7_b": 724, "secondary_b": 15, "c1_g": 315, "c1_b": 665, "c3_b": 675, "sch_mgmt_name": "Madarsa unrecognized", "c11": 34, "c10": 11, "total_pre_enrol": 7205, "c12": 2, "secondary_total": 33, "primary_b": 3337, "primary_g": 1334, "cpp_b": 58, "c11_g": 26, "total_g": 1755, "total_pre_b": 5378, "higher_secondary_total": 36, "total_b": 5320, "cpp_g": 72, "c11_b": 8, "c8_g": 104, "c4_g": 251, "c8_b": 555, "c6_g": 139, "c4_b": 673, "c2_g": 301, "total_pre_g": 1827, "c6_b": 679, "primary_total": 4671, "c2_b": 670}, {"category_name": "PS (I-V) ", "total_enrol": 60983, "upper_primary_b": 8992, "upper_primary_g": 7493, "higher_secondary_b": 3158, "loc_name": "Urban", "higher_secondary_g": 2919, "c10_g": 2159, "cpp": 0, "c12_g": 1365, "upper_primary_total": 16485, "c12_b": 1447, "c1": 5300, "c2": 5453, "c10_b": 2594, "c3": 5672, "c4": 5639, "c7_g": 2526, "secondary_g": 4751, "c5": 5622, "location_name": "Maharashtra", "c6": 5525, "c9_g": 2592, "c7": 5541, "c9_b": 3390, "c3_g": 2618, "c8": 5419, "c9": 5982, "c5_g": 2486, "c5_b": 3136, "c7_b": 3015, "secondary_b": 5984, "c1_g": 2487, "c1_b": 2813, "c3_b": 3054, "sch_mgmt_name": "Kendriya Vidyalaya / Central School", "c11": 3265, "c10": 4753, "total_pre_enrol": 60983, "c12": 2812, "secondary_total": 10735, "primary_b": 15013, "primary_g": 12673, "cpp_b": 0, "c11_g": 1554, "total_g": 27836, "total_pre_b": 33147, "higher_secondary_total": 6077, "total_b": 33147, "cpp_g": 0, "c11_b": 1711, "c8_g": 2483, "c4_g": 2520, "c8_b": 2936, "c6_g": 2484, "c4_b": 3119, "c2_g": 2562, "total_pre_g": 27836, "c6_b": 3041, "primary_total": 27686, "c2_b": 2891}, {"category_name": "PS (I-V) ", "total_enrol": 4767, "upper_primary_b": 845, "upper_primary_g": 800, "higher_secondary_b": 237, "loc_name": "Urban", "higher_secondary_g": 270, "c10_g": 248, "cpp": 0, "c12_g": 130, "upper_primary_total": 1645, "c12_b": 123, "c1": 288, "c2": 299, "c10_b": 253, "c3": 299, "c4": 295, "c7_g": 267, "secondary_g": 527, "c5": 350, "location_name": "Maharashtra", "c6": 548, "c9_g": 279, "c7": 544, "c9_b": 304, "c3_g": 146, "c8": 553, "c9": 583, "c5_g": 166, "c5_b": 184, "c7_b": 277, "secondary_b": 557, "c1_g": 133, "c1_b": 155, "c3_b": 153, "sch_mgmt_name": "Tribal Welfare Department", "c11": 254, "c10": 501, "total_pre_enrol": 4767, "c12": 253, "secondary_total": 1084, "primary_b": 788, "primary_g": 743, "cpp_b": 0, "c11_g": 140, "total_g": 2340, "total_pre_b": 2427, "higher_secondary_total": 507, "total_b": 2427, "cpp_g": 0, "c11_b": 114, "c8_g": 260, "c4_g": 150, "c8_b": 293, "c6_g": 273, "c4_b": 145, "c2_g": 148, "total_pre_g": 2340, "c6_b": 275, "primary_total": 1531, "c2_b": 151}, {"category_name": "PS (I-V) ", "total_enrol": 9838, "upper_primary_b": 1419, "upper_primary_g": 1184, "higher_secondary_b": 341, "loc_name": "Urban", "higher_secondary_g": 371, "c10_g": 405, "cpp": 0, "c12_g": 174, "upper_primary_total": 2603, "c12_b": 143, "c1": 944, "c2": 962, "c10_b": 411, "c3": 934, "c4": 937, "c7_g": 410, "secondary_g": 858, "c5": 956, "location_name": "Maharashtra", "c6": 906, "c9_g": 453, "c7": 925, "c9_b": 521, "c3_g": 437, "c8": 772, "c9": 974, "c5_g": 457, "c5_b": 499, "c7_b": 515, "secondary_b": 932, "c1_g": 420, "c1_b": 524, "c3_b": 497, "sch_mgmt_name": "Other Central Govt. Schools", "c11": 395, "c10": 816, "total_pre_enrol": 9838, "c12": 317, "secondary_total": 1790, "primary_b": 2587, "primary_g": 2146, "cpp_b": 0, "c11_g": 197, "total_g": 4559, "total_pre_b": 5279, "higher_secondary_total": 712, "total_b": 5279, "cpp_g": 0, "c11_b": 198, "c8_g": 346, "c4_g": 398, "c8_b": 426, "c6_g": 428, "c4_b": 539, "c2_g": 434, "total_pre_g": 4559, "c6_b": 478, "primary_total": 4733, "c2_b": 528}, {"category_name": "PS (I-V) ", "total_enrol": 2896, "upper_primary_b": 824, "upper_primary_g": 545, "higher_secondary_b": 348, "loc_name": "Urban", "higher_secondary_g": 225, "c10_g": 193, "cpp": 0, "c12_g": 119, "upper_primary_total": 1369, "c12_b": 166, "c1": 0, "c2": 0, "c10_b": 275, "c3": 0, "c4": 0, "c7_g": 184, "secondary_g": 406, "c5": 0, "location_name": "Maharashtra", "c6": 481, "c9_g": 213, "c7": 457, "c9_b": 273, "c3_g": 0, "c8": 431, "c9": 486, "c5_g": 0, "c5_b": 0, "c7_b": 273, "secondary_b": 548, "c1_g": 0, "c1_b": 0, "c3_b": 0, "sch_mgmt_name": "Jawahar Navodaya Vidyalaya ", "c11": 288, "c10": 468, "total_pre_enrol": 2896, "c12": 285, "secondary_total": 954, "primary_b": 0, "primary_g": 0, "cpp_b": 0, "c11_g": 106, "total_g": 1176, "total_pre_b": 1720, "higher_secondary_total": 573, "total_b": 1720, "cpp_g": 0, "c11_b": 182, "c8_g": 181, "c4_g": 0, "c8_b": 250, "c6_g": 180, "c4_b": 0, "c2_g": 0, "total_pre_g": 1176, "c6_b": 301, "primary_total": 0, "c2_b": 0}, {"category_name": "PS (I-V) ", "total_enrol": 650, "upper_primary_b": 292, "upper_primary_g": 6, "higher_secondary_b": 149, "loc_name": "Urban", "higher_secondary_g": 0, "c10_g": 2, "cpp": 0, "c12_g": 0, "upper_primary_total": 298, "c12_b": 61, "c1": 0, "c2": 0, "c10_b": 98, "c3": 0, "c4": 0, "c7_g": 2, "secondary_g": 4, "c5": 0, "location_name": "Maharashtra", "c6": 104, "c9_g": 2, "c7": 95, "c9_b": 101, "c3_g": 0, "c8": 99, "c9": 103, "c5_g": 0, "c5_b": 0, "c7_b": 93, "secondary_b": 199, "c1_g": 0, "c1_b": 0, "c3_b": 0, "sch_mgmt_name": "Sainik School", "c11": 88, "c10": 100, "total_pre_enrol": 650, "c12": 61, "secondary_total": 203, "primary_b": 0, "primary_g": 0, "cpp_b": 0, "c11_g": 0, "total_g": 10, "total_pre_b": 640, "higher_secondary_total": 149, "total_b": 640, "cpp_g": 0, "c11_b": 88, "c8_g": 2, "c4_g": 0, "c8_b": 97, "c6_g": 2, "c4_b": 0, "c2_g": 0, "total_pre_g": 10, "c6_b": 102, "primary_total": 0, "c2_b": 0}, {"category_name": "PS (I-V) ", "total_enrol": 4055291, "upper_primary_b": 559408, "upper_primary_g": 417061, "higher_secondary_b": 206166, "loc_name": "Urban", "higher_secondary_g": 162001, "c10_g": 114931, "cpp": 362091, "c12_g": 79414, "upper_primary_total": 976469, "c12_b": 102592, "c1": 460221, "c2": 449369, "c10_b": 150190, "c3": 441247, "c4": 436154, "c7_g": 137004, "secondary_g": 240645, "c5": 360698, "location_name": "Maharashtra", "c6": 342851, "c9_g": 125714, "c7": 322173, "c9_b": 172131, "c3_g": 194504, "c8": 311445, "c9": 297845, "c5_g": 154217, "c5_b": 206481, "c7_b": 185169, "secondary_b": 322321, "c1_g": 207963, "c1_b": 252258, "c3_b": 246743, "sch_mgmt_name": "Private Unaided (Recognized)", "c11": 186161, "c10": 265121, "total_pre_enrol": 4417382, "c12": 182006, "secondary_total": 562966, "primary_b": 1199155, "primary_g": 948534, "cpp_b": 195700, "c11_g": 82587, "total_g": 1768241, "total_pre_b": 2482750, "higher_secondary_total": 368167, "total_b": 2287050, "cpp_g": 166391, "c11_b": 103574, "c8_g": 133109, "c4_g": 191446, "c8_b": 178336, "c6_g": 146948, "c4_b": 244708, "c2_g": 200404, "total_pre_g": 1934632, "c6_b": 195903, "primary_total": 2147689, "c2_b": 248965}, {"category_name": "PS (I-V) ", "total_enrol": 87619, "upper_primary_b": 7468, "upper_primary_g": 6200, "higher_secondary_b": 47, "loc_name": "Urban", "higher_secondary_g": 56, "c10_g": 443, "cpp": 20072, "c12_g": 30, "upper_primary_total": 13668, "c12_b": 21, "c1": 19400, "c2": 16408, "c10_b": 679, "c3": 14437, "c4": 13506, "c7_g": 2211, "secondary_g": 1112, "c5": 7333, "location_name": "Maharashtra", "c6": 5856, "c9_g": 669, "c7": 4761, "c9_b": 973, "c3_g": 6649, "c8": 3051, "c9": 1642, "c5_g": 3304, "c5_b": 4029, "c7_b": 2550, "secondary_b": 1652, "c1_g": 9289, "c1_b": 10111, "c3_b": 7788, "sch_mgmt_name": "Unrecognized", "c11": 52, "c10": 1122, "total_pre_enrol": 107691, "c12": 51, "secondary_total": 2764, "primary_b": 37878, "primary_g": 33206, "cpp_b": 10567, "c11_g": 26, "total_g": 40574, "total_pre_b": 57612, "higher_secondary_total": 103, "total_b": 47045, "cpp_g": 9505, "c11_b": 26, "c8_g": 1301, "c4_g": 6249, "c8_b": 1750, "c6_g": 2688, "c4_b": 7257, "c2_g": 7715, "total_pre_g": 50079, "c6_b": 3168, "primary_total": 71084, "c2_b": 8693}], "staticFilter": null, "columnView": null, "columnDataType": null, "msData": null, "status": "0", "errorMessage": null, "jsonString": null, "yearList": ["2019-20", "2019-20", "2018-19", "2018-19", "2017-18", "2017-18", "2016-17", "2016-17", "2015-16", "2014-15", "2013-14", "2012-13"]}