{"columnName": ["code", "cat8", "cat9", "cat6", "cat7", "cat4", "locn_name", "cat5", "cat2", "cat3", "cat1", "cat10", "cat11", "Total"], "rowValue": [{"code": "1216", "cat8": 0, "cat9": 0, "cat6": 1, "cat7": 1, "cat4": 1, "locn_name": "ANJAW", "cat5": 0, "cat2": 26, "cat3": 2, "cat1": 55, "cat10": 0, "cat11": 0, "Total": 86}, {"code": "1212", "cat8": 0, "cat9": 0, "cat6": 20, "cat7": 2, "cat4": 2, "locn_name": "CHANGLANG", "cat5": 5, "cat2": 63, "cat3": 3, "cat1": 246, "cat10": 1, "cat11": 0, "Total": 342}, {"code": "1210", "cat8": 0, "cat9": 0, "cat6": 0, "cat7": 0, "cat4": 1, "locn_name": "DIBANG VALLEY", "cat5": 1, "cat2": 5, "cat3": 0, "cat1": 37, "cat10": 0, "cat11": 0, "Total": 44}, {"code": "1203", "cat8": 1, "cat9": 0, "cat6": 11, "cat7": 0, "cat4": 4, "locn_name": "EAST KAMENG", "cat5": 2, "cat2": 43, "cat3": 2, "cat1": 222, "cat10": 1, "cat11": 0, "Total": 286}, {"code": "1208", "cat8": 0, "cat9": 0, "cat6": 9, "cat7": 2, "cat4": 6, "locn_name": "EAST SIANG", "cat5": 2, "cat2": 64, "cat3": 1, "cat1": 89, "cat10": 3, "cat11": 0, "Total": 176}, {"code": "1219", "cat8": 0, "cat9": 0, "cat6": 4, "cat7": 1, "cat4": 3, "locn_name": "KRA DAADI", "cat5": 0, "cat2": 50, "cat3": 0, "cat1": 84, "cat10": 1, "cat11": 0, "Total": 143}, {"code": "1214", "cat8": 0, "cat9": 0, "cat6": 2, "cat7": 0, "cat4": 3, "locn_name": "KURUNG KUMEY", "cat5": 2, "cat2": 31, "cat3": 1, "cat1": 119, "cat10": 0, "cat11": 0, "Total": 158}, {"code": "1211", "cat8": 0, "cat9": 0, "cat6": 4, "cat7": 1, "cat4": 1, "locn_name": "LOHIT", "cat5": 1, "cat2": 30, "cat3": 1, "cat1": 60, "cat10": 0, "cat11": 0, "Total": 98}, {"code": "1217", "cat8": 0, "cat9": 0, "cat6": 1, "cat7": 2, "cat4": 3, "locn_name": "LONGDING", "cat5": 2, "cat2": 21, "cat3": 1, "cat1": 60, "cat10": 0, "cat11": 0, "Total": 90}, {"code": "1215", "cat8": 0, "cat9": 0, "cat6": 8, "cat7": 1, "cat4": 1, "locn_name": "LOWER DIBANG VALLEY", "cat5": 2, "cat2": 29, "cat3": 2, "cat1": 82, "cat10": 2, "cat11": 0, "Total": 127}, {"code": "1205", "cat8": 0, "cat9": 0, "cat6": 9, "cat7": 4, "cat4": 2, "locn_name": "LOWER SUBANSIRI", "cat5": 2, "cat2": 77, "cat3": 3, "cat1": 197, "cat10": 3, "cat11": 0, "Total": 297}, {"code": "1218", "cat8": 0, "cat9": 0, "cat6": 12, "cat7": 0, "cat4": 1, "locn_name": "NAMSAI", "cat5": 3, "cat2": 63, "cat3": 3, "cat1": 146, "cat10": 0, "cat11": 0, "Total": 228}, {"code": "1204", "cat8": 0, "cat9": 0, "cat6": 34, "cat7": 4, "cat4": 2, "locn_name": "PAPUM PARE", "cat5": 3, "cat2": 105, "cat3": 17, "cat1": 222, "cat10": 1, "cat11": 0, "Total": 388}, {"code": "1220", "cat8": 0, "cat9": 0, "cat6": 4, "cat7": 3, "cat4": 2, "locn_name": "SIANG", "cat5": 1, "cat2": 27, "cat3": 0, "cat1": 88, "cat10": 2, "cat11": 0, "Total": 127}, {"code": "1201", "cat8": 0, "cat9": 0, "cat6": 8, "cat7": 2, "cat4": 0, "locn_name": "TAWANG", "cat5": 1, "cat2": 44, "cat3": 2, "cat1": 76, "cat10": 0, "cat11": 0, "Total": 133}, {"code": "1213", "cat8": 0, "cat9": 0, "cat6": 8, "cat7": 0, "cat4": 1, "locn_name": "TIRAP", "cat5": 1, "cat2": 36, "cat3": 3, "cat1": 88, "cat10": 0, "cat11": 0, "Total": 137}, {"code": "1209", "cat8": 0, "cat9": 0, "cat6": 0, "cat7": 2, "cat4": 5, "locn_name": "UPPER SIANG", "cat5": 5, "cat2": 24, "cat3": 0, "cat1": 75, "cat10": 0, "cat11": 0, "Total": 111}, {"code": "1206", "cat8": 0, "cat9": 0, "cat6": 9, "cat7": 1, "cat4": 6, "locn_name": "UPPER SUBANSIRI", "cat5": 1, "cat2": 56, "cat3": 1, "cat1": 192, "cat10": 1, "cat11": 0, "Total": 267}, {"code": "1202", "cat8": 0, "cat9": 0, "cat6": 10, "cat7": 2, "cat4": 0, "locn_name": "WEST KAMENG", "cat5": 1, "cat2": 64, "cat3": 7, "cat1": 140, "cat10": 0, "cat11": 0, "Total": 224}, {"code": "1207", "cat8": 0, "cat9": 0, "cat6": 17, "cat7": 2, "cat4": 2, "locn_name": "WEST SIANG", "cat5": 4, "cat2": 64, "cat3": 5, "cat1": 182, "cat10": 1, "cat11": 0, "Total": 277}, {"code": "20", "cat8": 1, "cat9": 0, "cat6": 171, "cat7": 30, "cat4": 46, "locn_name": "Total", "cat5": 39, "cat2": 922, "cat3": 54, "cat1": 2460, "cat10": 16, "cat11": 0, "Total": 3739}], "staticFilter": null, "columnView": null, "columnDataType": null, "msData": null, "status": "0", "errorMessage": null, "jsonString": null, "yearList": ["2019-20", "2018-19", "2017-18", "2016-17", "2015-16", "2014-15", "2013-14", "2012-13"]}