{"columnName": ["cat8", "cat9", "cat6", "cat7", "cat4", "cat5", "sch_mgmt_id", "cat2", "cat3", "cat1", "cat10", "cat11", "Total", "sch_mgmt_name"], "rowValue": [{"cat8": 862, "cat9": 0, "cat6": 0, "cat7": 20, "cat4": 4, "cat5": 66, "sch_mgmt_id": 1, "cat2": 1, "cat3": 0, "cat1": 0, "cat10": 125, "cat11": 143, "Total": 1221, "sch_mgmt_name": "Department of Education"}, {"cat8": 102, "cat9": 0, "cat6": 27, "cat7": 26, "cat4": 8, "cat5": 53, "sch_mgmt_id": 2, "cat2": 644, "cat3": 4, "cat1": 1, "cat10": 67, "cat11": 1, "Total": 933, "sch_mgmt_name": "Tribal Welfare Department"}, {"cat8": 92, "cat9": 0, "cat6": 0, "cat7": 2, "cat4": 150, "cat5": 0, "sch_mgmt_id": 3, "cat2": 21745, "cat3": 0, "cat1": 10772, "cat10": 43, "cat11": 0, "Total": 32804, "sch_mgmt_name": "Local body"}, {"cat8": 1984, "cat9": 0, "cat6": 2, "cat7": 13, "cat4": 279, "cat5": 81, "sch_mgmt_id": 4, "cat2": 179, "cat3": 29, "cat1": 70, "cat10": 3040, "cat11": 57, "Total": 5734, "sch_mgmt_name": "Government Aided"}, {"cat8": 894, "cat9": 0, "cat6": 899, "cat7": 17, "cat4": 347, "cat5": 58, "sch_mgmt_id": 5, "cat2": 6344, "cat3": 1486, "cat1": 1757, "cat10": 1221, "cat11": 618, "Total": 13641, "sch_mgmt_name": "Private Unaided (Recognized)"}, {"cat8": 0, "cat9": 0, "cat6": 0, "cat7": 6, "cat4": 65, "cat5": 0, "sch_mgmt_id": 6, "cat2": 2, "cat3": 0, "cat1": 0, "cat10": 0, "cat11": 0, "Total": 73, "sch_mgmt_name": "Other Govt. managed schools"}, {"cat8": 14, "cat9": 0, "cat6": 0, "cat7": 0, "cat4": 0, "cat5": 0, "sch_mgmt_id": 90, "cat2": 45, "cat3": 0, "cat1": 1, "cat10": 26, "cat11": 0, "Total": 86, "sch_mgmt_name": "Social welfare Department"}, {"cat8": 0, "cat9": 0, "cat6": 8, "cat7": 0, "cat4": 0, "cat5": 0, "sch_mgmt_id": 92, "cat2": 5, "cat3": 37, "cat1": 0, "cat10": 0, "cat11": 0, "Total": 50, "sch_mgmt_name": "Kendriya Vidyalaya / Central School"}, {"cat8": 0, "cat9": 0, "cat6": 0, "cat7": 2, "cat4": 7, "cat5": 22, "sch_mgmt_id": 93, "cat2": 0, "cat3": 0, "cat1": 0, "cat10": 0, "cat11": 0, "Total": 31, "sch_mgmt_name": "Jawahar Navodaya Vidyalaya"}, {"cat8": 0, "cat9": 0, "cat6": 0, "cat7": 0, "cat4": 0, "cat5": 1, "sch_mgmt_id": 94, "cat2": 0, "cat3": 0, "cat1": 0, "cat10": 0, "cat11": 0, "Total": 1, "sch_mgmt_name": "Sainik School"}, {"cat8": 0, "cat9": 0, "cat6": 2, "cat7": 0, "cat4": 0, "cat5": 0, "sch_mgmt_id": 95, "cat2": 1, "cat3": 0, "cat1": 0, "cat10": 0, "cat11": 0, "Total": 3, "sch_mgmt_name": "Railway School"}, {"cat8": 0, "cat9": 0, "cat6": 1, "cat7": 0, "cat4": 0, "cat5": 0, "sch_mgmt_id": 97, "cat2": 0, "cat3": 2, "cat1": 0, "cat10": 1, "cat11": 0, "Total": 4, "sch_mgmt_name": "Madarsa recognized (by Wakf board/Madarsa Board) "}, {"cat8": 3948, "cat9": 0, "cat6": 939, "cat7": 86, "cat4": 860, "cat5": 281, "sch_mgmt_id": 582, "cat2": 28966, "cat3": 1558, "cat1": 12601, "cat10": 4523, "cat11": 819, "Total": 54581, "sch_mgmt_name": "Total"}], "staticFilter": null, "columnView": null, "columnDataType": null, "msData": null, "status": "1", "errorMessage": null, "jsonString": null, "yearList": ["2019-20", "2018-19", "2017-18", "2016-17", "2015-16", "2014-15", "2013-14", "2012-13"]}