{"columnName": ["cat8", "cat9", "cat6", "cat7", "cat4", "cat5", "sch_mgmt_id", "cat2", "cat3", "cat1", "cat10", "cat11", "Total", "sch_mgmt_name"], "rowValue": [{"cat8": 0, "cat9": 0, "cat6": 0, "cat7": 63, "cat4": 101, "cat5": 45, "sch_mgmt_id": 1, "cat2": 0, "cat3": 1, "cat1": 438, "cat10": 0, "cat11": 1, "Total": 649, "sch_mgmt_name": "Department of Education"}, {"cat8": 0, "cat9": 0, "cat6": 3, "cat7": 0, "cat4": 0, "cat5": 1, "sch_mgmt_id": 4, "cat2": 0, "cat3": 7, "cat1": 0, "cat10": 0, "cat11": 0, "Total": 11, "sch_mgmt_name": "Government Aided"}, {"cat8": 0, "cat9": 0, "cat6": 111, "cat7": 0, "cat4": 0, "cat5": 0, "sch_mgmt_id": 5, "cat2": 129, "cat3": 110, "cat1": 34, "cat10": 1, "cat11": 1, "Total": 386, "sch_mgmt_name": "Private Unaided (Recognized)"}, {"cat8": 0, "cat9": 0, "cat6": 0, "cat7": 0, "cat4": 0, "cat5": 0, "sch_mgmt_id": 6, "cat2": 0, "cat3": 1, "cat1": 0, "cat10": 0, "cat11": 0, "Total": 1, "sch_mgmt_name": "Other Govt. managed schools"}, {"cat8": 0, "cat9": 0, "cat6": 0, "cat7": 0, "cat4": 0, "cat5": 0, "sch_mgmt_id": 8, "cat2": 0, "cat3": 0, "cat1": 0, "cat10": 0, "cat11": 1, "Total": 1, "sch_mgmt_name": "Unrecognized"}, {"cat8": 0, "cat9": 0, "cat6": 0, "cat7": 0, "cat4": 0, "cat5": 0, "sch_mgmt_id": 92, "cat2": 0, "cat3": 5, "cat1": 0, "cat10": 0, "cat11": 0, "Total": 5, "sch_mgmt_name": "Kendriya Vidyalaya / Central School"}, {"cat8": 0, "cat9": 0, "cat6": 0, "cat7": 0, "cat4": 0, "cat5": 1, "sch_mgmt_id": 93, "cat2": 0, "cat3": 0, "cat1": 0, "cat10": 0, "cat11": 0, "Total": 1, "sch_mgmt_name": "Jawahar Navodaya Vidyalaya "}, {"cat8": 0, "cat9": 0, "cat6": 0, "cat7": 0, "cat4": 0, "cat5": 0, "sch_mgmt_id": 98, "cat2": 0, "cat3": 0, "cat1": 1, "cat10": 0, "cat11": 0, "Total": 1, "sch_mgmt_name": "Madarsa unrecognized"}, {"cat8": 0, "cat9": 0, "cat6": 114, "cat7": 63, "cat4": 101, "cat5": 47, "sch_mgmt_id": 307, "cat2": 129, "cat3": 124, "cat1": 473, "cat10": 1, "cat11": 3, "Total": 1055, "sch_mgmt_name": "Total"}], "staticFilter": null, "columnView": null, "columnDataType": null, "msData": null, "status": "1", "errorMessage": null, "jsonString": null, "yearList": ["2019-20", "2018-19", "2017-18", "2016-17", "2015-16", "2014-15", "2013-14", "2012-13"]}