{"columnName": ["cat8", "cat9", "cat6", "cat7", "cat4", "cat5", "sch_mgmt_id", "cat2", "cat3", "cat1", "cat10", "cat11", "Total", "sch_mgmt_name"], "rowValue": [{"cat8": 11, "cat9": 0, "cat6": 0, "cat7": 0, "cat4": 487, "cat5": 5, "sch_mgmt_id": 1, "cat2": 7, "cat3": 1, "cat1": 1075, "cat10": 2, "cat11": 0, "Total": 1588, "sch_mgmt_name": "Department of Education"}, {"cat8": 0, "cat9": 0, "cat6": 0, "cat7": 0, "cat4": 1, "cat5": 0, "sch_mgmt_id": 3, "cat2": 0, "cat3": 0, "cat1": 2, "cat10": 0, "cat11": 0, "Total": 3, "sch_mgmt_name": "Local body"}, {"cat8": 0, "cat9": 0, "cat6": 0, "cat7": 1, "cat4": 15, "cat5": 28, "sch_mgmt_id": 4, "cat2": 7, "cat3": 4, "cat1": 1, "cat10": 1, "cat11": 0, "Total": 57, "sch_mgmt_name": "Government Aided"}, {"cat8": 17, "cat9": 0, "cat6": 24, "cat7": 20, "cat4": 244, "cat5": 78, "sch_mgmt_id": 5, "cat2": 219, "cat3": 72, "cat1": 405, "cat10": 71, "cat11": 0, "Total": 1150, "sch_mgmt_name": "Private Unaided (Recognized)"}, {"cat8": 0, "cat9": 0, "cat6": 1, "cat7": 0, "cat4": 0, "cat5": 0, "sch_mgmt_id": 6, "cat2": 1, "cat3": 0, "cat1": 0, "cat10": 0, "cat11": 0, "Total": 2, "sch_mgmt_name": "Other Govt. managed schools"}, {"cat8": 0, "cat9": 0, "cat6": 0, "cat7": 0, "cat4": 1, "cat5": 0, "sch_mgmt_id": 8, "cat2": 0, "cat3": 0, "cat1": 0, "cat10": 0, "cat11": 0, "Total": 1, "sch_mgmt_name": "Unrecognized"}, {"cat8": 0, "cat9": 0, "cat6": 2, "cat7": 0, "cat4": 0, "cat5": 0, "sch_mgmt_id": 90, "cat2": 0, "cat3": 4, "cat1": 2, "cat10": 0, "cat11": 0, "Total": 8, "sch_mgmt_name": "Social welfare Department"}, {"cat8": 0, "cat9": 0, "cat6": 1, "cat7": 0, "cat4": 0, "cat5": 0, "sch_mgmt_id": 92, "cat2": 1, "cat3": 0, "cat1": 1, "cat10": 0, "cat11": 0, "Total": 3, "sch_mgmt_name": "Kendriya Vidyalaya / Central School"}, {"cat8": 0, "cat9": 0, "cat6": 47, "cat7": 3, "cat4": 12, "cat5": 2, "sch_mgmt_id": 97, "cat2": 72, "cat3": 8, "cat1": 470, "cat10": 0, "cat11": 0, "Total": 614, "sch_mgmt_name": "Madarsa recognized (by Wakf board/Madarsa Board) "}, {"cat8": 0, "cat9": 0, "cat6": 1, "cat7": 1, "cat4": 1, "cat5": 0, "sch_mgmt_id": 98, "cat2": 10, "cat3": 4, "cat1": 88, "cat10": 0, "cat11": 0, "Total": 105, "sch_mgmt_name": "Madarsa unrecognized"}, {"cat8": 28, "cat9": 0, "cat6": 76, "cat7": 25, "cat4": 761, "cat5": 113, "sch_mgmt_id": 404, "cat2": 317, "cat3": 93, "cat1": 2044, "cat10": 74, "cat11": 0, "Total": 3531, "sch_mgmt_name": "Total"}], "staticFilter": null, "columnView": null, "columnDataType": null, "msData": null, "status": "1", "errorMessage": null, "jsonString": null, "yearList": ["2019-20", "2018-19", "2017-18", "2016-17", "2015-16", "2014-15", "2013-14", "2012-13"]}