{"columnName": ["cat8", "cat9", "cat6", "cat7", "cat4", "cat5", "sch_mgmt_id", "cat2", "cat3", "cat1", "cat10", "cat11", "Total", "sch_mgmt_name"], "rowValue": [{"cat8": 10, "cat9": 0, "cat6": 11, "cat7": 13, "cat4": 0, "cat5": 0, "sch_mgmt_id": 1, "cat2": 1, "cat3": 0, "cat1": 0, "cat10": 0, "cat11": 1, "Total": 36, "sch_mgmt_name": "Department of Education"}, {"cat8": 0, "cat9": 0, "cat6": 1, "cat7": 1, "cat4": 0, "cat5": 0, "sch_mgmt_id": 2, "cat2": 0, "cat3": 0, "cat1": 0, "cat10": 0, "cat11": 0, "Total": 2, "sch_mgmt_name": "Tribal Welfare Department"}, {"cat8": 1, "cat9": 0, "cat6": 0, "cat7": 0, "cat4": 0, "cat5": 0, "sch_mgmt_id": 4, "cat2": 0, "cat3": 0, "cat1": 0, "cat10": 0, "cat11": 7, "Total": 8, "sch_mgmt_name": "Government Aided"}, {"cat8": 0, "cat9": 0, "cat6": 14, "cat7": 0, "cat4": 1, "cat5": 0, "sch_mgmt_id": 5, "cat2": 29, "cat3": 7, "cat1": 9, "cat10": 0, "cat11": 5, "Total": 65, "sch_mgmt_name": "Private Unaided (Recognized)"}, {"cat8": 0, "cat9": 0, "cat6": 0, "cat7": 0, "cat4": 0, "cat5": 0, "sch_mgmt_id": 6, "cat2": 0, "cat3": 0, "cat1": 0, "cat10": 0, "cat11": 0, "Total": 0, "sch_mgmt_name": "Other Govt. managed schools"}, {"cat8": 1, "cat9": 0, "cat6": 1, "cat7": 1, "cat4": 0, "cat5": 0, "sch_mgmt_id": 8, "cat2": 7, "cat3": 0, "cat1": 3, "cat10": 0, "cat11": 0, "Total": 13, "sch_mgmt_name": "Unrecognized"}, {"cat8": 0, "cat9": 0, "cat6": 0, "cat7": 0, "cat4": 0, "cat5": 0, "sch_mgmt_id": 90, "cat2": 0, "cat3": 0, "cat1": 0, "cat10": 0, "cat11": 0, "Total": 0, "sch_mgmt_name": "Social welfare Department"}, {"cat8": 0, "cat9": 0, "cat6": 0, "cat7": 0, "cat4": 0, "cat5": 0, "sch_mgmt_id": 92, "cat2": 1, "cat3": 1, "cat1": 0, "cat10": 0, "cat11": 0, "Total": 2, "sch_mgmt_name": "Kendriya Vidyalaya / Central School"}, {"cat8": 0, "cat9": 0, "cat6": 0, "cat7": 0, "cat4": 0, "cat5": 1, "sch_mgmt_id": 93, "cat2": 0, "cat3": 0, "cat1": 0, "cat10": 0, "cat11": 0, "Total": 1, "sch_mgmt_name": "Jawahar Navodaya Vidyalaya "}, {"cat8": 12, "cat9": 0, "cat6": 27, "cat7": 15, "cat4": 1, "cat5": 1, "sch_mgmt_id": 301, "cat2": 38, "cat3": 8, "cat1": 12, "cat10": 0, "cat11": 13, "Total": 127, "sch_mgmt_name": "Total"}], "staticFilter": null, "columnView": null, "columnDataType": null, "msData": null, "status": "1", "errorMessage": null, "jsonString": null, "yearList": ["2019-20", "2018-19", "2017-18", "2016-17", "2015-16", "2014-15", "2013-14", "2012-13"]}