{"columnName": ["cat8", "cat9", "cat6", "cat7", "cat4", "cat5", "sch_mgmt_id", "cat2", "cat3", "cat1", "cat10", "cat11", "Total", "sch_mgmt_name"], "rowValue": [{"cat8": 18, "cat9": 0, "cat6": 0, "cat7": 0, "cat4": 639, "cat5": 9, "sch_mgmt_id": 1, "cat2": 0, "cat3": 0, "cat1": 2004, "cat10": 0, "cat11": 0, "Total": 2670, "sch_mgmt_name": "Department of Education"}, {"cat8": 0, "cat9": 0, "cat6": 0, "cat7": 0, "cat4": 1, "cat5": 0, "sch_mgmt_id": 2, "cat2": 0, "cat3": 0, "cat1": 40, "cat10": 0, "cat11": 0, "Total": 41, "sch_mgmt_name": "Tribal Welfare Department"}, {"cat8": 0, "cat9": 0, "cat6": 0, "cat7": 0, "cat4": 0, "cat5": 1, "sch_mgmt_id": 3, "cat2": 0, "cat3": 1, "cat1": 0, "cat10": 0, "cat11": 0, "Total": 2, "sch_mgmt_name": "Local body"}, {"cat8": 3, "cat9": 0, "cat6": 1, "cat7": 13, "cat4": 71, "cat5": 59, "sch_mgmt_id": 4, "cat2": 5, "cat3": 5, "cat1": 4, "cat10": 17, "cat11": 0, "Total": 178, "sch_mgmt_name": "Government Aided"}, {"cat8": 149, "cat9": 0, "cat6": 9, "cat7": 32, "cat4": 159, "cat5": 64, "sch_mgmt_id": 5, "cat2": 88, "cat3": 14, "cat1": 299, "cat10": 142, "cat11": 0, "Total": 956, "sch_mgmt_name": "Private Unaided (Recognized)"}, {"cat8": 0, "cat9": 0, "cat6": 0, "cat7": 0, "cat4": 0, "cat5": 1, "sch_mgmt_id": 92, "cat2": 0, "cat3": 1, "cat1": 0, "cat10": 0, "cat11": 0, "Total": 2, "sch_mgmt_name": "Kendriya Vidyalaya / Central School"}, {"cat8": 1, "cat9": 0, "cat6": 16, "cat7": 0, "cat4": 1, "cat5": 0, "sch_mgmt_id": 97, "cat2": 39, "cat3": 13, "cat1": 28, "cat10": 0, "cat11": 0, "Total": 98, "sch_mgmt_name": "Madarsa recognized (by Wakf board/Madarsa Board) "}, {"cat8": 0, "cat9": 0, "cat6": 2, "cat7": 0, "cat4": 1, "cat5": 0, "sch_mgmt_id": 98, "cat2": 15, "cat3": 3, "cat1": 9, "cat10": 0, "cat11": 0, "Total": 30, "sch_mgmt_name": "Madarsa unrecognized"}, {"cat8": 171, "cat9": 0, "cat6": 28, "cat7": 45, "cat4": 872, "cat5": 134, "sch_mgmt_id": 302, "cat2": 147, "cat3": 37, "cat1": 2384, "cat10": 159, "cat11": 0, "Total": 3977, "sch_mgmt_name": "Total"}], "staticFilter": null, "columnView": null, "columnDataType": null, "msData": null, "status": "1", "errorMessage": null, "jsonString": null, "yearList": ["2019-20", "2018-19", "2017-18", "2016-17", "2015-16", "2014-15", "2013-14", "2012-13"]}