{"columnName": ["cat8", "cat9", "cat6", "cat7", "cat4", "cat5", "sch_mgmt_id", "cat2", "cat3", "cat1", "cat10", "cat11", "Total", "sch_mgmt_name"], "rowValue": [{"cat8": 14, "cat9": 0, "cat6": 0, "cat7": 0, "cat4": 570, "cat5": 8, "sch_mgmt_id": 1, "cat2": 5, "cat3": 0, "cat1": 1204, "cat10": 2, "cat11": 0, "Total": 1803, "sch_mgmt_name": "Department of Education"}, {"cat8": 0, "cat9": 0, "cat6": 0, "cat7": 3, "cat4": 9, "cat5": 19, "sch_mgmt_id": 4, "cat2": 1, "cat3": 2, "cat1": 1, "cat10": 4, "cat11": 0, "Total": 39, "sch_mgmt_name": "Government Aided"}, {"cat8": 14, "cat9": 0, "cat6": 11, "cat7": 16, "cat4": 115, "cat5": 31, "sch_mgmt_id": 5, "cat2": 130, "cat3": 24, "cat1": 341, "cat10": 30, "cat11": 0, "Total": 712, "sch_mgmt_name": "Private Unaided (Recognized)"}, {"cat8": 0, "cat9": 0, "cat6": 0, "cat7": 0, "cat4": 0, "cat5": 1, "sch_mgmt_id": 92, "cat2": 1, "cat3": 1, "cat1": 0, "cat10": 0, "cat11": 0, "Total": 3, "sch_mgmt_name": "Kendriya Vidyalaya / Central School"}, {"cat8": 0, "cat9": 0, "cat6": 0, "cat7": 0, "cat4": 3, "cat5": 0, "sch_mgmt_id": 97, "cat2": 125, "cat3": 0, "cat1": 97, "cat10": 0, "cat11": 0, "Total": 225, "sch_mgmt_name": "Madarsa recognized (by Wakf board/Madarsa Board) "}, {"cat8": 28, "cat9": 0, "cat6": 11, "cat7": 19, "cat4": 697, "cat5": 59, "sch_mgmt_id": 199, "cat2": 262, "cat3": 27, "cat1": 1643, "cat10": 36, "cat11": 0, "Total": 2782, "sch_mgmt_name": "Total"}], "staticFilter": null, "columnView": null, "columnDataType": null, "msData": null, "status": "1", "errorMessage": null, "jsonString": null, "yearList": ["2019-20", "2018-19", "2017-18", "2016-17", "2015-16", "2014-15", "2013-14", "2012-13"]}