{"columnName": ["cat8", "cat9", "cat6", "cat7", "cat4", "cat5", "sch_mgmt_id", "cat2", "cat3", "cat1", "cat10", "cat11", "Total", "sch_mgmt_name"], "rowValue": [{"cat8": 17, "cat9": 0, "cat6": 0, "cat7": 0, "cat4": 799, "cat5": 11, "sch_mgmt_id": 1, "cat2": 0, "cat3": 0, "cat1": 2006, "cat10": 6, "cat11": 0, "Total": 2839, "sch_mgmt_name": "Department of Education"}, {"cat8": 1, "cat9": 0, "cat6": 0, "cat7": 8, "cat4": 15, "cat5": 33, "sch_mgmt_id": 4, "cat2": 18, "cat3": 0, "cat1": 5, "cat10": 2, "cat11": 0, "Total": 82, "sch_mgmt_name": "Government Aided"}, {"cat8": 9, "cat9": 0, "cat6": 19, "cat7": 31, "cat4": 65, "cat5": 64, "sch_mgmt_id": 5, "cat2": 240, "cat3": 32, "cat1": 380, "cat10": 25, "cat11": 0, "Total": 865, "sch_mgmt_name": "Private Unaided (Recognized)"}, {"cat8": 0, "cat9": 0, "cat6": 0, "cat7": 0, "cat4": 0, "cat5": 1, "sch_mgmt_id": 90, "cat2": 0, "cat3": 1, "cat1": 4, "cat10": 0, "cat11": 0, "Total": 6, "sch_mgmt_name": "Social welfare Department"}, {"cat8": 0, "cat9": 0, "cat6": 0, "cat7": 0, "cat4": 0, "cat5": 0, "sch_mgmt_id": 92, "cat2": 0, "cat3": 1, "cat1": 0, "cat10": 0, "cat11": 0, "Total": 1, "sch_mgmt_name": "Kendriya Vidyalaya / Central School"}, {"cat8": 0, "cat9": 0, "cat6": 0, "cat7": 0, "cat4": 0, "cat5": 1, "sch_mgmt_id": 93, "cat2": 0, "cat3": 0, "cat1": 0, "cat10": 0, "cat11": 0, "Total": 1, "sch_mgmt_name": "Jawahar Navodaya Vidyalaya"}, {"cat8": 0, "cat9": 0, "cat6": 18, "cat7": 0, "cat4": 0, "cat5": 0, "sch_mgmt_id": 97, "cat2": 34, "cat3": 3, "cat1": 189, "cat10": 0, "cat11": 0, "Total": 244, "sch_mgmt_name": "Madarsa recognized (by Wakf board/Madarsa Board) "}, {"cat8": 27, "cat9": 0, "cat6": 37, "cat7": 39, "cat4": 879, "cat5": 110, "sch_mgmt_id": 382, "cat2": 292, "cat3": 37, "cat1": 2584, "cat10": 33, "cat11": 0, "Total": 4038, "sch_mgmt_name": "Total"}], "staticFilter": null, "columnView": null, "columnDataType": null, "msData": null, "status": "1", "errorMessage": null, "jsonString": null, "yearList": ["2019-20", "2018-19", "2017-18", "2016-17", "2015-16", "2014-15", "2013-14", "2012-13"]}