{"columnName": ["cat8", "cat9", "cat6", "cat7", "cat4", "cat5", "sch_mgmt_id", "cat2", "cat3", "cat1", "cat10", "cat11", "Total", "sch_mgmt_name"], "rowValue": [{"cat8": 0, "cat9": 0, "cat6": 17, "cat7": 143, "cat4": 29, "cat5": 442, "sch_mgmt_id": 1, "cat2": 4, "cat3": 374, "cat1": 0, "cat10": 0, "cat11": 0, "Total": 1009, "sch_mgmt_name": "Department of Education"}, {"cat8": 0, "cat9": 0, "cat6": 1, "cat7": 0, "cat4": 0, "cat5": 0, "sch_mgmt_id": 2, "cat2": 1, "cat3": 2, "cat1": 1, "cat10": 0, "cat11": 0, "Total": 5, "sch_mgmt_name": "Tribal Welfare Department"}, {"cat8": 0, "cat9": 0, "cat6": 10, "cat7": 0, "cat4": 0, "cat5": 1, "sch_mgmt_id": 3, "cat2": 9, "cat3": 14, "cat1": 1729, "cat10": 0, "cat11": 0, "Total": 1763, "sch_mgmt_name": "Local body"}, {"cat8": 0, "cat9": 0, "cat6": 12, "cat7": 14, "cat4": 12, "cat5": 68, "sch_mgmt_id": 4, "cat2": 12, "cat3": 90, "cat1": 48, "cat10": 1, "cat11": 1, "Total": 258, "sch_mgmt_name": "Government Aided"}, {"cat8": 0, "cat9": 0, "cat6": 250, "cat7": 8, "cat4": 5, "cat5": 10, "sch_mgmt_id": 5, "cat2": 908, "cat3": 497, "cat1": 991, "cat10": 0, "cat11": 0, "Total": 2669, "sch_mgmt_name": "Private Unaided (Recognized)"}, {"cat8": 0, "cat9": 0, "cat6": 0, "cat7": 0, "cat4": 0, "cat5": 0, "sch_mgmt_id": 6, "cat2": 1, "cat3": 1, "cat1": 1, "cat10": 2, "cat11": 0, "Total": 5, "sch_mgmt_name": "Other Govt. managed schools"}, {"cat8": 0, "cat9": 0, "cat6": 6, "cat7": 0, "cat4": 0, "cat5": 2, "sch_mgmt_id": 7, "cat2": 2, "cat3": 36, "cat1": 0, "cat10": 0, "cat11": 0, "Total": 46, "sch_mgmt_name": "Central Govt"}, {"cat8": 0, "cat9": 0, "cat6": 296, "cat7": 165, "cat4": 46, "cat5": 523, "sch_mgmt_id": 28, "cat2": 937, "cat3": 1014, "cat1": 2770, "cat10": 3, "cat11": 1, "Total": 5755, "sch_mgmt_name": "Total"}], "staticFilter": null, "columnView": null, "columnDataType": null, "msData": null, "status": "1", "errorMessage": null, "jsonString": null, "yearList": ["2019-20", "2018-19", "2017-18", "2016-17", "2015-16", "2014-15", "2013-14", "2012-13"]}