{"columnName": ["total_enrol", "upper_primary_b", "upper_primary_g", "higher_secondary_b", "higher_secondary_g", "c10_g", "cpp", "c12_g", "upper_primary_total", "c12_b", "c1", "c2", "c10_b", "c3", "c4", "c7_g", "secondary_g", "c5", "location_name", "c6", "c9_g", "c7", "c9_b", "c3_g", "c8", "c9", "c5_g", "c5_b", "c7_b", "secondary_b", "c1_g", "c1_b", "c3_b", "c11", "c10", "total_pre_enrol", "c12", "secondary_total", "primary_b", "primary_g", "cpp_b", "c11_g", "total_g", "total_pre_b", "higher_secondary_total", "total_b", "item_name", "cpp_g", "c11_b", "c8_g", "c4_g", "c8_b", "c6_g", "c4_b", "c2_g", "total_pre_g", "c6_b", "primary_total", "c2_b"], "rowValue": [{"total_enrol": 113206, "upper_primary_b": 16597, "upper_primary_g": 15140, "higher_secondary_b": 5054, "higher_secondary_g": 5634, "c10_g": 4590, "cpp": 0, "c12_g": 2782, "upper_primary_total": 31737, "c12_b": 2491, "c1": 9244, "c2": 10270, "c10_b": 4980, "c3": 10079, "c4": 10578, "c7_g": 5035, "secondary_g": 9664, "c5": 10632, "location_name": "ANANTAPUR", "c6": 10712, "c9_g": 5074, "c7": 10543, "c9_b": 5334, "c3_g": 4259, "c8": 10482, "c9": 10408, "c5_g": 4937, "c5_b": 5695, "c7_b": 5508, "secondary_b": 10314, "c1_g": 4365, "c1_b": 4879, "c3_b": 5820, "c11": 5415, "c10": 9570, "total_pre_enrol": 113206, "c12": 5273, "secondary_total": 19978, "primary_b": 27795, "primary_g": 23008, "cpp_b": 0, "c11_g": 2852, "total_g": 53446, "total_pre_b": 59760, "higher_secondary_total": 10688, "total_b": 59760, "item_name": "General", "cpp_g": 0, "c11_b": 2563, "c8_g": 5063, "c4_g": 4853, "c8_b": 5419, "c6_g": 5042, "c4_b": 5725, "c2_g": 4594, "total_pre_g": 53446, "c6_b": 5670, "primary_total": 50803, "c2_b": 5676}, {"total_enrol": 395200, "upper_primary_b": 54124, "upper_primary_g": 50379, "higher_secondary_b": 18721, "higher_secondary_g": 17677, "c10_g": 15128, "cpp": 0, "c12_g": 8069, "upper_primary_total": 104503, "c12_b": 8356, "c1": 38483, "c2": 39361, "c10_b": 16044, "c3": 38557, "c4": 36841, "c7_g": 16543, "secondary_g": 30860, "c5": 37231, "location_name": "ANANTAPUR", "c6": 36205, "c9_g": 15732, "c7": 34244, "c9_b": 16922, "c3_g": 16325, "c8": 34054, "c9": 32654, "c5_g": 17633, "c5_b": 19598, "c7_b": 17701, "secondary_b": 32966, "c1_g": 18434, "c1_b": 20049, "c3_b": 22232, "c11": 19973, "c10": 31172, "total_pre_enrol": 395200, "c12": 16425, "secondary_total": 63826, "primary_b": 103089, "primary_g": 87384, "cpp_b": 0, "c11_g": 9608, "total_g": 186300, "total_pre_b": 208900, "higher_secondary_total": 36398, "total_b": 208900, "item_name": "OBC", "cpp_g": 0, "c11_b": 10365, "c8_g": 16572, "c4_g": 17217, "c8_b": 17482, "c6_g": 17264, "c4_b": 19624, "c2_g": 17775, "total_pre_g": 186300, "c6_b": 18941, "primary_total": 190473, "c2_b": 21586}, {"total_enrol": 107772, "upper_primary_b": 14633, "upper_primary_g": 13959, "higher_secondary_b": 5089, "higher_secondary_g": 5264, "c10_g": 4590, "cpp": 0, "c12_g": 2264, "upper_primary_total": 28592, "c12_b": 2100, "c1": 10332, "c2": 10225, "c10_b": 4523, "c3": 9802, "c4": 9591, "c7_g": 4622, "secondary_g": 9395, "c5": 10060, "location_name": "ANANTAPUR", "c6": 9647, "c9_g": 4805, "c7": 9470, "c9_b": 4899, "c3_g": 4307, "c8": 9475, "c9": 9704, "c5_g": 4893, "c5_b": 5167, "c7_b": 4848, "secondary_b": 9422, "c1_g": 5103, "c1_b": 5229, "c3_b": 5495, "c11": 5989, "c10": 9113, "total_pre_enrol": 107772, "c12": 4364, "secondary_total": 18817, "primary_b": 26257, "primary_g": 23753, "cpp_b": 0, "c11_g": 3000, "total_g": 52371, "total_pre_b": 55401, "higher_secondary_total": 10353, "total_b": 55401, "item_name": "SC", "cpp_g": 0, "c11_b": 2989, "c8_g": 4659, "c4_g": 4665, "c8_b": 4816, "c6_g": 4678, "c4_b": 4926, "c2_g": 4785, "total_pre_g": 52371, "c6_b": 4969, "primary_total": 50010, "c2_b": 5440}, {"total_enrol": 28024, "upper_primary_b": 3962, "upper_primary_g": 3625, "higher_secondary_b": 1187, "higher_secondary_g": 1085, "c10_g": 1026, "cpp": 0, "c12_g": 476, "upper_primary_total": 7587, "c12_b": 543, "c1": 2660, "c2": 2648, "c10_b": 1119, "c3": 2726, "c4": 2725, "c7_g": 1227, "secondary_g": 2155, "c5": 2833, "location_name": "ANANTAPUR", "c6": 2670, "c9_g": 1129, "c7": 2555, "c9_b": 1299, "c3_g": 1147, "c8": 2362, "c9": 2428, "c5_g": 1318, "c5_b": 1515, "c7_b": 1328, "secondary_b": 2418, "c1_g": 1303, "c1_b": 1357, "c3_b": 1579, "c11": 1253, "c10": 2145, "total_pre_enrol": 28024, "c12": 1019, "secondary_total": 4573, "primary_b": 7404, "primary_g": 6188, "cpp_b": 0, "c11_g": 609, "total_g": 13053, "total_pre_b": 14971, "higher_secondary_total": 2272, "total_b": 14971, "item_name": "ST", "cpp_g": 0, "c11_b": 644, "c8_g": 1103, "c4_g": 1271, "c8_b": 1259, "c6_g": 1295, "c4_b": 1454, "c2_g": 1149, "total_pre_g": 13053, "c6_b": 1375, "primary_total": 13592, "c2_b": 1499}], "staticFilter": null, "columnView": null, "columnDataType": null, "msData": null, "status": "0", "errorMessage": null, "jsonString": null, "yearList": ["2019-20", "2018-19", "2017-18", "2016-17", "2015-16", "2014-15", "2013-14", "2012-13"]}