{"columnName": ["total_enrol", "upper_primary_b", "upper_primary_g", "higher_secondary_b", "higher_secondary_g", "c10_g", "cpp", "c12_g", "upper_primary_total", "c12_b", "c1", "c2", "c10_b", "c3", "c4", "c7_g", "secondary_g", "c5", "location_name", "c6", "c9_g", "c7", "c9_b", "c3_g", "c8", "c9", "c5_g", "c5_b", "c7_b", "secondary_b", "c1_g", "c1_b", "c3_b", "c11", "c10", "total_pre_enrol", "c12", "secondary_total", "primary_b", "primary_g", "cpp_b", "c11_g", "total_g", "total_pre_b", "higher_secondary_total", "total_b", "item_name", "cpp_g", "c11_b", "c8_g", "c4_g", "c8_b", "c6_g", "c4_b", "c2_g", "total_pre_g", "c6_b", "primary_total", "c2_b"], "rowValue": [{"total_enrol": 262805, "upper_primary_b": 37348, "upper_primary_g": 36670, "higher_secondary_b": 12782, "higher_secondary_g": 13274, "c10_g": 10344, "cpp": 18219, "c12_g": 6271, "upper_primary_total": 74018, "c12_b": 5827, "c1": 23364, "c2": 23952, "c10_b": 10228, "c3": 24437, "c4": 24926, "c7_g": 12694, "secondary_g": 21355, "c5": 23882, "location_name": "EAST GODAVARI", "c6": 24593, "c9_g": 11011, "c7": 25489, "c9_b": 10587, "c3_g": 11842, "c8": 23936, "c9": 21598, "c5_g": 11716, "c5_b": 12166, "c7_b": 12795, "secondary_b": 20815, "c1_g": 11163, "c1_b": 12201, "c3_b": 12595, "c11": 13958, "c10": 20572, "total_pre_enrol": 281024, "c12": 12098, "secondary_total": 42170, "primary_b": 62276, "primary_g": 58285, "cpp_b": 9740, "c11_g": 7003, "total_g": 129584, "total_pre_b": 142961, "higher_secondary_total": 26056, "total_b": 133221, "item_name": "General", "cpp_g": 8479, "c11_b": 6955, "c8_g": 11886, "c4_g": 12111, "c8_b": 12050, "c6_g": 12090, "c4_b": 12815, "c2_g": 11453, "total_pre_g": 138063, "c6_b": 12503, "primary_total": 120561, "c2_b": 12499}, {"total_enrol": 358703, "upper_primary_b": 48668, "upper_primary_g": 49149, "higher_secondary_b": 16031, "higher_secondary_g": 16246, "c10_g": 12375, "cpp": 17993, "c12_g": 7283, "upper_primary_total": 97817, "c12_b": 7063, "c1": 34521, "c2": 35254, "c10_b": 12267, "c3": 36506, "c4": 36014, "c7_g": 16938, "secondary_g": 25981, "c5": 34659, "location_name": "EAST GODAVARI", "c6": 33626, "c9_g": 13606, "c7": 33597, "c9_b": 13407, "c3_g": 17722, "c8": 30594, "c9": 27013, "c5_g": 17209, "c5_b": 17450, "c7_b": 16659, "secondary_b": 25674, "c1_g": 16865, "c1_b": 17656, "c3_b": 18784, "c11": 17931, "c10": 24642, "total_pre_enrol": 376696, "c12": 14346, "secondary_total": 51655, "primary_b": 90273, "primary_g": 86681, "cpp_b": 9932, "c11_g": 8963, "total_g": 178057, "total_pre_b": 190578, "higher_secondary_total": 32277, "total_b": 180646, "item_name": "OBC", "cpp_g": 8061, "c11_b": 8968, "c8_g": 15472, "c4_g": 17799, "c8_b": 15122, "c6_g": 16739, "c4_b": 18215, "c2_g": 17086, "total_pre_g": 186118, "c6_b": 16887, "primary_total": 176954, "c2_b": 18168}, {"total_enrol": 177066, "upper_primary_b": 23217, "upper_primary_g": 23061, "higher_secondary_b": 9170, "higher_secondary_g": 11084, "c10_g": 6155, "cpp": 5987, "c12_g": 5255, "upper_primary_total": 46278, "c12_b": 4011, "c1": 17302, "c2": 17209, "c10_b": 5616, "c3": 17696, "c4": 17103, "c7_g": 7979, "secondary_g": 12660, "c5": 16563, "location_name": "EAST GODAVARI", "c6": 16014, "c9_g": 6505, "c7": 15756, "c9_b": 6385, "c3_g": 8667, "c8": 14508, "c9": 12890, "c5_g": 8243, "c5_b": 8320, "c7_b": 7777, "secondary_b": 12001, "c1_g": 8505, "c1_b": 8797, "c3_b": 9029, "c11": 10988, "c10": 11771, "total_pre_enrol": 183053, "c12": 9266, "secondary_total": 24661, "primary_b": 43691, "primary_g": 42182, "cpp_b": 3336, "c11_g": 5829, "total_g": 88987, "total_pre_b": 91415, "higher_secondary_total": 20254, "total_b": 88079, "item_name": "SC", "cpp_g": 2651, "c11_b": 5159, "c8_g": 7255, "c4_g": 8414, "c8_b": 7253, "c6_g": 7827, "c4_b": 8689, "c2_g": 8353, "total_pre_g": 91638, "c6_b": 8187, "primary_total": 85873, "c2_b": 8856}, {"total_enrol": 45628, "upper_primary_b": 5297, "upper_primary_g": 5471, "higher_secondary_b": 2289, "higher_secondary_g": 3184, "c10_g": 1530, "cpp": 615, "c12_g": 1481, "upper_primary_total": 10768, "c12_b": 1075, "c1": 4930, "c2": 4767, "c10_b": 1055, "c3": 5084, "c4": 4752, "c7_g": 1870, "secondary_g": 3182, "c5": 4310, "location_name": "EAST GODAVARI", "c6": 3923, "c9_g": 1652, "c7": 3597, "c9_b": 1307, "c3_g": 2404, "c8": 3248, "c9": 2959, "c5_g": 2104, "c5_b": 2206, "c7_b": 1727, "secondary_b": 2362, "c1_g": 2454, "c1_b": 2476, "c3_b": 2680, "c11": 2917, "c10": 2585, "total_pre_enrol": 46243, "c12": 2556, "secondary_total": 5544, "primary_b": 12111, "primary_g": 11732, "cpp_b": 332, "c11_g": 1703, "total_g": 23569, "total_pre_b": 22391, "higher_secondary_total": 5473, "total_b": 22059, "item_name": "ST", "cpp_g": 283, "c11_b": 1214, "c8_g": 1661, "c4_g": 2366, "c8_b": 1587, "c6_g": 1940, "c4_b": 2386, "c2_g": 2404, "total_pre_g": 23852, "c6_b": 1983, "primary_total": 23843, "c2_b": 2363}], "staticFilter": null, "columnView": null, "columnDataType": null, "msData": null, "status": "0", "errorMessage": null, "jsonString": null, "yearList": ["2019-20", "2018-19", "2017-18", "2016-17", "2015-16", "2014-15", "2013-14", "2012-13"]}